distfeatselect/__init__.py
distfeatselect/dfs.py
distfeatselect/rfs.py
distfeatselect/utils.py
distfeatselect-0.1.4.dist-info/LICENSE
distfeatselect-0.1.4.dist-info/METADATA
distfeatselect-0.1.4.dist-info/WHEEL
distfeatselect-0.1.4.dist-info/top_level.txt
distfeatselect-0.1.4.dist-info/RECORD
