Metadata-Version: 2.1
Name: distfeatselect
Version: 0.1.4
Summary: A Pyhton package implementing distributed feature selection algorithm.
Home-page: https://github.com/dkudumovic1/distfeatselect
Download-URL: https://github.com/dkudumovic1/distfeatselect/archive/refs/tags/0.1.4.tar.gz
Author: Dzeneta Kudumovic
Author-email: dzeneta.kudum@gmail.com
License: MIT
Project-URL: Documentation, https://dkudumovic1.github.io/distfeatselect/
Keywords: feature selection,distributed feature selection,randomised feature selection
Classifier: Development Status :: 4 - Beta
Classifier: Intended Audience :: Science/Research
Classifier: Topic :: Scientific/Engineering :: Artificial Intelligence
Classifier: License :: OSI Approved :: MIT License
Classifier: Programming Language :: Python :: 3
License-File: LICENSE
Requires-Dist: numpy
Requires-Dist: pandas
Requires-Dist: statsmodels
Requires-Dist: scikit-learn
Requires-Dist: dcor
